nonconform/__init__.py
nonconform/adapters.py
nonconform/detector.py
nonconform/fdr.py
nonconform/resampling.py
nonconform/scoring.py
nonconform/structures.py
nonconform/weighting.py
nonconform/_internal/__init__.py
nonconform/_internal/config.py
nonconform/_internal/constants.py
nonconform/_internal/log_utils.py
nonconform/_internal/math_utils.py
nonconform/_internal/tuning.py
nonconform-0.98.3.dist-info/METADATA
nonconform-0.98.3.dist-info/WHEEL
nonconform-0.98.3.dist-info/licenses/LICENSE
nonconform-0.98.3.dist-info/RECORD
