Metadata-Version: 2.4
Name: nonconform
Version: 0.98.3
Summary: Conformal Anomaly Detection
Project-URL: Homepage, https://github.com/OliverHennhoefer/nonconform
Project-URL: Documentation, https://oliverhennhoefer.github.io/nonconform/
Project-URL: Bugs, https://github.com/OliverHennhoefer/nonconform/issues
Project-URL: Changelog, https://github.com/OliverHennhoefer/nonconform/blob/main/CHANGELOG.md
Author-email: Oliver Hennhoefer <oliver.hennhoefer@mail.de>
Maintainer-email: Oliver Hennhoefer <oliver.hennhoefer@mail.de>
License: BSD 3-Clause License
License-File: LICENSE
Keywords: anomaly detection,conformal anomaly detection,conformal inference,false discovery rate,uncertainty quantification
Classifier: Development Status :: 4 - Beta
Classifier: Intended Audience :: Developers
Classifier: Intended Audience :: Science/Research
Classifier: License :: OSI Approved :: BSD License
Classifier: Operating System :: OS Independent
Classifier: Programming Language :: Python :: 3.12
Classifier: Programming Language :: Python :: 3.13
Classifier: Topic :: Scientific/Engineering :: Artificial Intelligence
Classifier: Topic :: Scientific/Engineering :: Information Analysis
Requires-Python: >=3.12
Requires-Dist: kdepy>=1.1.12
Requires-Dist: numpy<2.3,>=2.2.0
Requires-Dist: optuna>=4.5.0
Requires-Dist: pandas>=2.2.1
Requires-Dist: scikit-learn<1.6,>=1.5.2
Requires-Dist: scipy>=1.13.0
Requires-Dist: tqdm>=4.66.2
Provides-Extra: all
Requires-Dist: oddball>=1.3.0; extra == 'all'
Requires-Dist: online-fdr>=0.0.3; extra == 'all'
Requires-Dist: pyarrow>=16.1.0; extra == 'all'
Requires-Dist: pyod==2.0.5; extra == 'all'
Provides-Extra: data
Requires-Dist: oddball>=1.3.0; extra == 'data'
Requires-Dist: pyarrow>=16.1.0; extra == 'data'
Provides-Extra: fdr
Requires-Dist: online-fdr>=0.0.3; extra == 'fdr'
Provides-Extra: pyod
Requires-Dist: pyod==2.0.5; extra == 'pyod'
